{
  "architectures": [
    "amd64",
    "arm64"
  ],
  "description": "resilio-sync - это приложение на основе Docker, которое обеспечивает быструю и безопасную синхронизацию и обмен файлами.",
  "screenshot_link": [
    "apps/resilio-sync/assets/screenshot-1.webp"
  ],
  "tagline": "Разблокируйте мощь безупречной синхронизации файлов.",
  "author": "self",
  "category": "Productivity",
  "hostname": "",
  "store_app_id": "resilio-sync",
  "base_url": "https://cdn.jsdelivr.net/gh/jerrykuku/ZimaOS-AppStore@gh-pages/"
}