{
  "architectures": [
    "amd64",
    "386",
    "arm64",
    "arm"
  ],
  "author": "CasaOS Team",
  "category": "Productivity",
  "description": "WebDAV - это веб-протокол, который позволяет вам обмениваться файлами и управлять ими через Интернет, обеспечивая совместную среду для редактирования файлов и контроля версий.",
  "developer": "CasaOS Team",
  "screenshot_link": [
    "apps/webdav/assets/screenshot-1.webp"
  ],
  "tagline": "Веб-протокол обмена и управления файлами",
  "tips": {
    "before_install": ""
  },
  "base_url": "https://cdn.jsdelivr.net/gh/jerrykuku/ZimaOS-AppStore@gh-pages/"
}